geo/__init__.py
geo/core/__init__.py
geo/core/coords.py
geo/core/io.py
geo/core/utils.py
geo/dem_camera/__init__.py
geo/dem_camera/dem_provider.py
geo/dem_camera/locator.py
geo/dem_camera/models.py
geo/dem_camera/spatial_index.py
geo/plugins/__init__.py
ags_geolocation-0.1.0.dist-info/METADATA
ags_geolocation-0.1.0.dist-info/WHEEL
ags_geolocation-0.1.0.dist-info/entry_points.txt
ags_geolocation-0.1.0.dist-info/RECORD
