Metadata-Version: 2.4
Name: ags-geolocation
Version: 0.1.0
Summary: Advanced geolocation service Python library.
Author-email: Your Name <you@example.com>
Requires-Python: >=3.9
Provides-Extra: dem-cam
Requires-Dist: lru-dict>=1.1; extra == 'dem-cam'
Requires-Dist: opencv-python>=4.8.0; extra == 'dem-cam'
Requires-Dist: pydantic>=2.0; extra == 'dem-cam'
Requires-Dist: pyproj>=3.4.0; extra == 'dem-cam'
Requires-Dist: rasterio>=1.3.0; extra == 'dem-cam'
Requires-Dist: rtree>=1.0; extra == 'dem-cam'
